configparser_rb/__init__.py
configparser_rb/core.py
configparser_rb/locale/configparser_rb.pot
configparser_rb/locale/es/LC_MESSAGES/configparser_rb.mo
configparser_rb/locale/es.po
configparser_rb/locale/es.po~
configparser_rb/poethepoet.py
configparser_rb/rotatedbase64.py
configparser_rb/tests/test_core.py
configparser_rb/tests/test_rotatedbase64.py
configparser_rb-1.0.0.dist-info/METADATA
configparser_rb-1.0.0.dist-info/WHEEL
configparser_rb-1.0.0.dist-info/entry_points.txt
configparser_rb-1.0.0.dist-info/licenses/LICENSE
configparser_rb-1.0.0.dist-info/RECORD
