Metadata-Version: 2.4
Name: configparser_rb
Version: 1.0.0
Summary: Config parser with the ability to obfuscate keys with rotated bits in base64
License-Expression: GPL-3.0
License-File: LICENSE
Author: turulomio
Author-email: turulomio@yahoo.es
Requires-Python: >=3.9,<4
Classifier: Programming Language :: Python :: 3
Classifier: Programming Language :: Python :: 3.9
Classifier: Programming Language :: Python :: 3.10
Classifier: Programming Language :: Python :: 3.11
Classifier: Programming Language :: Python :: 3.12
Classifier: Programming Language :: Python :: 3.13
Classifier: Programming Language :: Python :: 3.14
Requires-Dist: pydicts (>=1.1.0,<2.0.0)
Project-URL: Homepage, https://github.com/turulomio/configparser_rb/
Project-URL: Repository, https://github.com/turulomio/configparser_rb/
Project-URL: changelog, https://github.com/turulomio/configparser_rb#changelog
